{
  "type": "FeatureCollection",
  "features": [
    {
      "type": "Feature",
      "geometry": {
        "type": "Point",
        "coordinates": [
          "2.95803000000000",
          "42.8934400000000"
        ]
      },
      "properties": {
        "name": "Col du Pré",
        "altitude": "142",
        "climbs": [
          {
            "done": false,
            "start": "Fitou",
            "length": "2.00",
            "moyen": "6.1",
            "max": "10.0",
            "profil": "",
            "category": 4
          }
        ],
        "mountain": "corbieres"
      }
    },
    {
      "type": "Feature",
      "geometry": {
        "type": "Point",
        "coordinates": [
          "2.85521000000000",
          "42.9993000000000"
        ]
      },
      "properties": {
        "name": "Col de Mandourelle",
        "altitude": "170",
        "climbs": [
          {
            "done": false,
            "start": "Villesèque des Corbières",
            "length": "1.00",
            "moyen": "3.2",
            "max": "0.0",
            "profil": "",
            "category": 5
          }
        ],
        "mountain": "corbieres"
      }
    },
    {
      "type": "Feature",
      "geometry": {
        "type": "Point",
        "coordinates": [
          "2.79991000000000",
          "42.9560300000000"
        ]
      },
      "properties": {
        "name": "Col de Canteloup",
        "altitude": "243",
        "climbs": [
          {
            "done": false,
            "start": "Embres et Castelmaure",
            "length": "2.00",
            "moyen": "3.15",
            "max": "0.0",
            "profil": "",
            "category": 5
          }
        ],
        "mountain": "corbieres"
      }
    },
    {
      "type": "Feature",
      "geometry": {
        "type": "Point",
        "coordinates": [
          "2.90711000000000",
          "42.8956900000000"
        ]
      },
      "properties": {
        "name": "Col de la Peira Dreita",
        "altitude": "243",
        "climbs": [
          {
            "done": false,
            "start": "Feuilla",
            "length": "7.00",
            "moyen": "1.04",
            "max": "0.0",
            "profil": "",
            "category": 5
          }
        ],
        "mountain": "corbieres"
      }
    },
    {
      "type": "Feature",
      "geometry": {
        "type": "Point",
        "coordinates": [
          "2.86898000000000",
          "42.9674900000000"
        ]
      },
      "properties": {
        "name": "Col de Péreille",
        "altitude": "245",
        "climbs": [
          {
            "done": false,
            "start": "Fraïsse des Corbières",
            "length": "1.30",
            "moyen": "6.54",
            "max": "0.0",
            "profil": "",
            "category": 4
          }
        ],
        "mountain": "corbieres"
      }
    },
    {
      "type": "Feature",
      "geometry": {
        "type": "Point",
        "coordinates": [
          "2.88135000000000",
          "42.9384800000000"
        ]
      },
      "properties": {
        "name": "Col de Feuilla",
        "altitude": "250",
        "climbs": [
          {
            "done": false,
            "start": "Feuilla",
            "length": "2.00",
            "moyen": "4",
            "max": "0.0",
            "profil": "",
            "category": 5
          }
        ],
        "mountain": "corbieres"
      }
    },
    {
      "type": "Feature",
      "geometry": {
        "type": "Point",
        "coordinates": [
          "2.75409000000000",
          "42.9313900000000"
        ]
      },
      "properties": {
        "name": "Col d'Extrême",
        "altitude": "251",
        "climbs": [
          {
            "done": false,
            "start": "Villeneuve des Corbières",
            "length": "6.00",
            "moyen": "1.85",
            "max": "6.0",
            "profil": "",
            "category": 5
          }
        ],
        "mountain": "corbieres"
      }
    },
    {
      "type": "Feature",
      "geometry": {
        "type": "Point",
        "coordinates": [
          "2.88747000000000",
          "42.9844700000000"
        ]
      },
      "properties": {
        "name": "Col de Souil",
        "altitude": "267",
        "climbs": [
          {
            "done": false,
            "start": "Sigean",
            "length": "11.00",
            "moyen": "2.34",
            "max": "10.0",
            "profil": "",
            "category": 4
          }
        ],
        "mountain": "corbieres"
      }
    },
    {
      "type": "Feature",
      "geometry": {
        "type": "Point",
        "coordinates": [
          "2.56514000000000",
          "43.1580000000000"
        ]
      },
      "properties": {
        "name": "Col de l'Alaric",
        "altitude": "317",
        "climbs": [
          {
            "done": false,
            "start": "Capendu",
            "length": "5.00",
            "moyen": "4.64",
            "max": "0.0",
            "profil": "https://profils.cols-cyclisme.com/1518.svg",
            "category": 3
          },
          {
            "done": false,
            "start": "Montlaur",
            "length": "4.00",
            "moyen": "3",
            "max": "0.0",
            "profil": "",
            "category": 4
          }
        ],
        "mountain": "corbieres"
      }
    },
    {
      "type": "Feature",
      "geometry": {
        "type": "Point",
        "coordinates": [
          "2.64776000000000",
          "43.0071300000000"
        ]
      },
      "properties": {
        "name": "Col du Prat",
        "altitude": "366",
        "climbs": [
          {
            "done": false,
            "start": "Villerouge Termenes",
            "length": "1.80",
            "moyen": "2.39",
            "max": "0.0",
            "profil": "",
            "category": 5
          }
        ],
        "mountain": "corbieres"
      }
    },
    {
      "type": "Feature",
      "geometry": {
        "type": "Point",
        "coordinates": [
          "2.62215000000000",
          "42.9953900000000"
        ]
      },
      "properties": {
        "name": "Col de la Tranchée",
        "altitude": "372",
        "climbs": [
          {
            "done": false,
            "start": "Villerouge Termenes",
            "length": "2.00",
            "moyen": "2.5",
            "max": "0.0",
            "profil": "",
            "category": 5
          }
        ],
        "mountain": "corbieres"
      }
    },
    {
      "type": "Feature",
      "geometry": {
        "type": "Point",
        "coordinates": [
          "2.69110000000000",
          "42.9649400000000"
        ]
      },
      "properties": {
        "name": "Col d'Amiel",
        "altitude": "378",
        "climbs": [
          {
            "done": false,
            "start": "Quintillan",
            "length": "1.50",
            "moyen": "4.13",
            "max": "0.0",
            "profil": "",
            "category": 5
          }
        ],
        "mountain": "corbieres"
      }
    },
    {
      "type": "Feature",
      "geometry": {
        "type": "Point",
        "coordinates": [
          "2.63396000000000",
          "43.0158600000000"
        ]
      },
      "properties": {
        "name": "Col de Villerouge",
        "altitude": "404",
        "climbs": [
          {
            "done": false,
            "start": "Talairan",
            "length": "5.00",
            "moyen": "4.48",
            "max": "0.0",
            "profil": "",
            "category": 3
          }
        ],
        "mountain": "corbieres"
      }
    },
    {
      "type": "Feature",
      "geometry": {
        "type": "Point",
        "coordinates": [
          "2.61270000000000",
          "42.9600400000000"
        ]
      },
      "properties": {
        "name": "Col des Liges",
        "altitude": "406",
        "climbs": [
          {
            "done": false,
            "start": "Davejean",
            "length": "1.00",
            "moyen": "7",
            "max": "7.0",
            "profil": "",
            "category": 4
          }
        ],
        "mountain": "corbieres"
      }
    },
    {
      "type": "Feature",
      "geometry": {
        "type": "Point",
        "coordinates": [
          "2.66934000000000",
          "42.9593700000000"
        ]
      },
      "properties": {
        "name": "Col de la Gineste",
        "altitude": "416",
        "climbs": [
          {
            "done": false,
            "start": "Palairac",
            "length": "1.00",
            "moyen": "5.2",
            "max": "0.0",
            "profil": "",
            "category": 5
          }
        ],
        "mountain": "corbieres"
      }
    },
    {
      "type": "Feature",
      "geometry": {
        "type": "Point",
        "coordinates": [
          "2.64995000000000",
          "42.9393000000000"
        ]
      },
      "properties": {
        "name": "Col de Ferréol",
        "altitude": "431",
        "climbs": [
          {
            "done": false,
            "start": "Maisons",
            "length": "2.90",
            "moyen": "3.45",
            "max": "0.0",
            "profil": "",
            "category": 5
          }
        ],
        "mountain": "corbieres"
      }
    },
    {
      "type": "Feature",
      "geometry": {
        "type": "Point",
        "coordinates": [
          "2.58077000000000",
          "42.9736300000000"
        ]
      },
      "properties": {
        "name": "Col de Bedos",
        "altitude": "485",
        "climbs": [
          {
            "done": false,
            "start": "Felines Termenes",
            "length": "3.80",
            "moyen": "3.82",
            "max": "0.0",
            "profil": "",
            "category": 4
          }
        ],
        "mountain": "corbieres"
      }
    },
    {
      "type": "Feature",
      "geometry": {
        "type": "Point",
        "coordinates": [
          "2.63762000000000",
          "42.9484100000000"
        ]
      },
      "properties": {
        "name": "Col de Couisse",
        "altitude": "507",
        "climbs": [
          {
            "done": false,
            "start": "Maisons",
            "length": "4.80",
            "moyen": "4.1",
            "max": "0.0",
            "profil": "",
            "category": 3
          },
          {
            "done": false,
            "start": "Felines Termenes",
            "length": "6.00",
            "moyen": "2.78",
            "max": "0.0",
            "profil": "",
            "category": 4
          }
        ],
        "mountain": "corbieres"
      }
    },
    {
      "type": "Feature",
      "geometry": {
        "type": "Point",
        "coordinates": [
          "2.58135000000000",
          "42.9947800000000"
        ]
      },
      "properties": {
        "name": "Col de Termes",
        "altitude": "520",
        "climbs": [
          {
            "done": false,
            "start": "Termes",
            "length": "3.50",
            "moyen": "5",
            "max": "6.5",
            "profil": "https://profils.cols-cyclisme.com/1488.svg",
            "category": 3
          }
        ],
        "mountain": "corbieres"
      }
    },
    {
      "type": "Feature",
      "geometry": {
        "type": "Point",
        "coordinates": [
          "2.44052000000000",
          "43.0620100000000"
        ]
      },
      "properties": {
        "name": "Col de la Garoullière",
        "altitude": "557",
        "climbs": [
          {
            "done": false,
            "start": "Labastide en val",
            "length": "5.60",
            "moyen": "5.71",
            "max": "9.0",
            "profil": "https://profils.cols-cyclisme.com/2781.gif",
            "category": 2
          },
          {
            "done": false,
            "start": "Clermont sur Lauquet",
            "length": "4.70",
            "moyen": "4.68",
            "max": "8.0",
            "profil": "https://profils.cols-cyclisme.com/2782.gif",
            "category": 3
          }
        ],
        "mountain": "corbieres"
      }
    },
    {
      "type": "Feature",
      "geometry": {
        "type": "Point",
        "coordinates": [
          "2.54284000000000",
          "42.9604400000000"
        ]
      },
      "properties": {
        "name": "Col des Fourches",
        "altitude": "565",
        "climbs": [
          {
            "done": false,
            "start": "Laroque de Fa",
            "length": "2.40",
            "moyen": "3.33",
            "max": "0.0",
            "profil": "",
            "category": 5
          }
        ],
        "mountain": "corbieres"
      }
    },
    {
      "type": "Feature",
      "geometry": {
        "type": "Point",
        "coordinates": [
          "2.45391000000000",
          "43.0250200000000"
        ]
      },
      "properties": {
        "name": "Col de la Louviero",
        "altitude": "599",
        "climbs": [
          {
            "done": false,
            "start": "D212 / D40",
            "length": "6.60",
            "moyen": "5.91",
            "max": "10.0",
            "profil": "https://profils.cols-cyclisme.com/2780.gif",
            "category": 2
          }
        ],
        "mountain": "corbieres"
      }
    },
    {
      "type": "Feature",
      "geometry": {
        "type": "Point",
        "coordinates": [
          "2.50709000000000",
          "42.9077500000000"
        ]
      },
      "properties": {
        "name": "Col de la Redoulade",
        "altitude": "705",
        "climbs": [
          {
            "done": false,
            "start": "Savignan",
            "length": "7.12",
            "moyen": "4.02",
            "max": "7.0",
            "profil": "https://profils.cols-cyclisme.com/2619.gif",
            "category": 3
          },
          {
            "done": false,
            "start": "Soulatgé",
            "length": "5.82",
            "moyen": "5.4",
            "max": "9.0",
            "profil": "https://profils.cols-cyclisme.com/2620.gif",
            "category": 3
          }
        ],
        "mountain": "corbieres"
      }
    },
    {
      "type": "Feature",
      "geometry": {
        "type": "Point",
        "coordinates": [
          "2.66923000000000",
          "42.7267700000000"
        ]
      },
      "properties": {
        "name": "Col de la Bataille",
        "altitude": "265",
        "climbs": [
          {
            "done": false,
            "start": "Estagel",
            "length": "7.10",
            "moyen": "2.55",
            "max": "4.2",
            "profil": "https://profils.cols-cyclisme.com/1376.gif",
            "category": 4
          }
        ],
        "mountain": "corbieres"
      }
    },
    {
      "type": "Feature",
      "geometry": {
        "type": "Point",
        "coordinates": [
          "2.86804000000000",
          "42.8827100000000"
        ]
      },
      "properties": {
        "name": "Col de la Sabine",
        "altitude": "373",
        "climbs": [
          {
            "done": false,
            "start": "Opoul",
            "length": "4.00",
            "moyen": "5.05",
            "max": "0.0",
            "profil": "",
            "category": 3
          }
        ],
        "mountain": "corbieres"
      }
    },
    {
      "type": "Feature",
      "geometry": {
        "type": "Point",
        "coordinates": [
          "2.67937600000000",
          "42.9099200000000"
        ]
      },
      "properties": {
        "name": "Mont Tauch",
        "altitude": "878",
        "climbs": [
          {
            "done": false,
            "start": "Tuchan",
            "length": "7.80",
            "moyen": "8.97",
            "max": "18.0",
            "profil": "https://profils.cols-cyclisme.com/859.gif",
            "category": 0
          }
        ],
        "mountain": "corbieres"
      }
    },
    {
      "type": "Feature",
      "geometry": {
        "type": "Point",
        "coordinates": [
          "2.69971800000000",
          "42.7271850000000"
        ]
      },
      "properties": {
        "name": "Força Réal",
        "altitude": "507",
        "climbs": [
          {
            "done": false,
            "start": "Millas",
            "length": "9.02",
            "moyen": "4.49",
            "max": "23.0",
            "profil": "https://profils.cols-cyclisme.com/1377.gif",
            "category": 2
          }
        ],
        "mountain": "corbieres"
      }
    },
    {
      "type": "Feature",
      "geometry": {
        "type": "Point",
        "coordinates": [
          "2.49452200000000",
          "43.1233740000000"
        ]
      },
      "properties": {
        "name": "Col d'Arquettes",
        "altitude": "427",
        "climbs": [
          {
            "done": false,
            "start": "Arquettes en Val",
            "length": "4.00",
            "moyen": "6.68",
            "max": "0.0",
            "profil": "",
            "category": 3
          }
        ],
        "mountain": "corbieres"
      }
    },
    {
      "type": "Feature",
      "geometry": {
        "type": "Point",
        "coordinates": [
          "2.81949700000000",
          "43.0399100000000"
        ]
      },
      "properties": {
        "name": "Pic de Saint-Victor",
        "altitude": "420",
        "climbs": [
          {
            "done": false,
            "start": "Ripaud",
            "length": "8.00",
            "moyen": "4",
            "max": "15.0",
            "profil": "",
            "category": 3
          }
        ],
        "mountain": "corbieres"
      }
    },
    {
      "type": "Feature",
      "geometry": {
        "type": "Point",
        "coordinates": [
          "2.86475200000000",
          "42.9181620000000"
        ]
      },
      "properties": {
        "name": "Montoulie de Périllou",
        "altitude": "697",
        "climbs": [
          {
            "done": false,
            "start": "Perillos",
            "length": "8.00",
            "moyen": "4.93",
            "max": "0.0",
            "profil": "",
            "category": 2
          }
        ],
        "mountain": "corbieres"
      }
    },
    {
      "type": "Feature",
      "geometry": {
        "type": "Point",
        "coordinates": [
          "2.85998400000000",
          "43.0307980000000"
        ]
      },
      "properties": {
        "name": "Col de Gleon",
        "altitude": "193",
        "climbs": [
          {
            "done": false,
            "start": "Gléon",
            "length": "2.00",
            "moyen": "6.5",
            "max": "0.0",
            "profil": "",
            "category": 3
          }
        ],
        "mountain": "corbieres"
      }
    },
    {
      "type": "Feature",
      "geometry": {
        "type": "Point",
        "coordinates": [
          "2.87285100000000",
          "43.0319210000000"
        ]
      },
      "properties": {
        "name": "Col Couloumi",
        "altitude": "290",
        "climbs": [
          {
            "done": false,
            "start": "Les Campets",
            "length": "3.00",
            "moyen": "8.33",
            "max": "0.0",
            "profil": "",
            "category": 2
          }
        ],
        "mountain": "corbieres"
      }
    },
    {
      "type": "Feature",
      "geometry": {
        "type": "Point",
        "coordinates": [
          "2.62121700000000",
          "42.8390970000000"
        ]
      },
      "properties": {
        "name": "Château de Queribus",
        "altitude": "602",
        "climbs": [
          {
            "done": false,
            "start": "Maury",
            "length": "7.00",
            "moyen": "6.4",
            "max": "17.0",
            "profil": "https://profils.cols-cyclisme.com/1850.gif",
            "category": 1
          },
          {
            "done": false,
            "start": "Cucugnan",
            "length": "3.34",
            "moyen": "9.07",
            "max": "16.0",
            "profil": "https://profils.cols-cyclisme.com/2618.gif",
            "category": 1
          }
        ],
        "mountain": "corbieres"
      }
    },
    {
      "type": "Feature",
      "geometry": {
        "type": "Point",
        "coordinates": [
          "2.55924700000000",
          "42.8703910000000"
        ]
      },
      "properties": {
        "name": "Château de Peyrepertuse",
        "altitude": "693",
        "climbs": [
          {
            "done": false,
            "start": "Duilhac sous Peyrepertuse",
            "length": "4.14",
            "moyen": "8.65",
            "max": "16.0",
            "profil": "https://profils.cols-cyclisme.com/1851.gif",
            "category": 1
          }
        ],
        "mountain": "corbieres"
      }
    },
    {
      "type": "Feature",
      "geometry": {
        "type": "Point",
        "coordinates": [
          "2.49644500000000",
          "43.1678850000000"
        ]
      },
      "properties": {
        "name": "La Petite Alaric",
        "altitude": "377",
        "climbs": [
          {
            "done": false,
            "start": "Barbaira",
            "length": "4.70",
            "moyen": "6.23",
            "max": "14.0",
            "profil": "https://profils.cols-cyclisme.com/2246.gif",
            "category": 2
          }
        ],
        "mountain": "corbieres"
      }
    },
    {
      "type": "Feature",
      "geometry": {
        "type": "Point",
        "coordinates": [
          "2.37959000000000",
          "42.9757800000000"
        ]
      },
      "properties": {
        "name": "Col de Valmigère",
        "altitude": "705",
        "climbs": [
          {
            "done": false,
            "start": "Arques",
            "length": "5.49",
            "moyen": "6.1",
            "max": "7.1",
            "profil": "https://profils.cols-cyclisme.com/3242.gif",
            "category": 2
          }
        ],
        "mountain": "corbieres"
      }
    },
    {
      "type": "Feature",
      "geometry": {
        "type": "Point",
        "coordinates": [
          "2.46453000000000",
          "43.1030800000000"
        ]
      },
      "properties": {
        "name": "Col de Taurize",
        "altitude": "498",
        "climbs": [
          {
            "done": false,
            "start": "Villar en Val",
            "length": "4.66",
            "moyen": "4.87",
            "max": "5.3",
            "profil": "https://profils.cols-cyclisme.com/3243.gif",
            "category": 3
          }
        ],
        "mountain": "corbieres"
      }
    }
  ]
}